morphZ/Nth_TC.py
morphZ/__init__.py
morphZ/_version.py
morphZ/bridge.py
morphZ/bridge_multiprocess.py
morphZ/bw_method.py
morphZ/dependency_tree.py
morphZ/kde_base.py
morphZ/morph.py
morphZ/morph_group.py
morphZ/morph_indep.py
morphZ/morph_pairwise.py
morphZ/morph_tree.py
morphZ/utils.py
morphz-0.3.7.1.dist-info/licenses/LICENSE
morphz-0.3.7.1.dist-info/METADATA
morphz-0.3.7.1.dist-info/WHEEL
morphz-0.3.7.1.dist-info/top_level.txt
morphz-0.3.7.1.dist-info/RECORD
