Metadata-Version: 2.4
Name: morphZ
Version: 0.3.7.1
Summary: Morph-Z for high accuracy marginal likelihood estimation package.
License: BSD-3-Clause
Project-URL: Repository, https://github.com/ApokryphaV1/MorphZ.git
Project-URL: Homepage, https://github.com/ApokryphaV1/MorphZ
Project-URL: Issues, https://github.com/ApokryphaV1/MorphZ/issues
Classifier: License :: OSI Approved :: BSD License
Classifier: Programming Language :: Python :: 3
Classifier: Programming Language :: Python :: 3 :: Only
Classifier: Programming Language :: Python :: 3.10
Classifier: Programming Language :: Python :: 3.11
Classifier: Programming Language :: Python :: 3.12
Classifier: Intended Audience :: Science/Research
Classifier: Topic :: Scientific/Engineering :: Information Analysis
Requires-Python: >=3.10
License-File: LICENSE
Requires-Dist: matplotlib
Requires-Dist: corner
Requires-Dist: networkx
Requires-Dist: numpy
Requires-Dist: scipy
Requires-Dist: emcee
Requires-Dist: statsmodels
Requires-Dist: scikit-learn
Provides-Extra: docs
Requires-Dist: jupyter-book<2; extra == "docs"
Provides-Extra: test
Requires-Dist: pytest; extra == "test"
Dynamic: license-file
